{
  "quiet": true,
  "legacyWatch": false,
  "delay": 0.1,
  "watch": [
    "../.env",
    ".browserslistrc",
    ".editorconfig",
    ".env",
    ".eslint.config.mjs",
    ".prettierignore",
    ".prettierrc",
    "config",
    "babel-node.config.js",
    "next.config.ts",
    "package.json",
    "postcss.config.js",
    "src",
    "tsconfig.json",
    "webpack.config.js",
    "yarn.lock"
  ],
  "ext": "js,jsx,ts,tsx,json,flow,css,scss,sass,styl,html,ejs,d,txt,yml,sh",
  "ignore": ["**/*.test.*s", "**/*.test.*sx", "**/__tests__", ".build", ".next", "node_modules", ".cache"],
  "exec": "run-s -c prod:clean prod:start:profile || cd ."
}
