{
  "acknowledgements": {
    "20A.EU1": {
      "numChunks": 155
    },
    "20A.EU2": {
      "numChunks": 29
    },
    "20H.Beta.V2": {
      "numChunks": 21
    },
    "20I.Alpha.V1": {
      "numChunks": 798
    },
    "20J.Gamma.V3": {
      "numChunks": 28
    },
    "21A.21B": {
      "numChunks": 33
    },
    "21A.Delta": {
      "numChunks": 29
    },
    "21B.Kappa": {
      "numChunks": 3
    },
    "21C.Epsilon": {
      "numChunks": 41
    },
    "21D.Eta": {
      "numChunks": 6
    },
    "21F.Iota": {
      "numChunks": 32
    },
    "ORF1a.S3675": {
      "numChunks": 906
    },
    "S.A626S": {
      "numChunks": 2
    },
    "S.D80Y": {
      "numChunks": 1
    },
    "S.E484": {
      "numChunks": 99
    },
    "S.H655": {
      "numChunks": 34
    },
    "S.H69-": {
      "numChunks": 831
    },
    "S.K417": {
      "numChunks": 24
    },
    "S.L18": {
      "numChunks": 113
    },
    "S.N439K": {
      "numChunks": 26
    },
    "S.N501": {
      "numChunks": 863
    },
    "S.P681": {
      "numChunks": 895
    },
    "S.Q677": {
      "numChunks": 34
    },
    "S.Q677H.Bluebird": {
      "numChunks": 1
    },
    "S.Q677H.Heron": {
      "numChunks": 1
    },
    "S.Q677H.Mockingbird": {
      "numChunks": 1
    },
    "S.Q677H.Quail": {
      "numChunks": 1
    },
    "S.Q677H.Robin1": {
      "numChunks": 6
    },
    "S.Q677H.Robin2": {
      "numChunks": 3
    },
    "S.Q677H.Yellowhammer": {
      "numChunks": 1
    },
    "S.Q677P.Pelican": {
      "numChunks": 5
    },
    "S.Q677R.Roadrunner": {
      "numChunks": 1
    },
    "S.S477": {
      "numChunks": 58
    },
    "S.S98F": {
      "numChunks": 15
    },
    "S.V1122L": {
      "numChunks": 1
    },
    "S.Y144-": {
      "numChunks": 813
    },
    "S.Y453F": {
      "numChunks": 2
    }
  }
}