{"France": "True", "Belgium": "True", "Germany": "True", "Netherlands": "True", "Spain": "True", "United Kingdom": "True", "Switzerland": "True", "Ireland": "True", "Norway": "True", "Denmark": "True", "Italy": "True", "Iceland": "True", "Sweden": "True", "USA": "True", "Latvia": "True", "Austria": "True", "Lithuania": "True", "Luxembourg": "True", "Portugal": "True", "Slovenia": "True", "Hungary": "True", "Canada": "True", "Finland": "True", "Poland": "True", "India": "True", "Slovakia": "True", "Australia": "True", "Japan": "True", "Singapore": "True", "Bulgaria": "True", "South Korea": "True", "Israel": "True", "Brazil": "True", "Turkey": "True", "Greece": "True", "Mexico": "True", "Czech Republic": "True", "North Macedonia": "True", "Romania": "True", "Aruba": "True", "Croatia": "True", "Estonia": "True", "Curacao": "True", "South Africa": "True", "Bangladesh": "True", "Chile": "True", "Qatar": "True", "Colombia": "True", "Nigeria": "True", "Egypt": "True", "Russia": "True", "Zimbabwe": "True", "Ghana": "True", "Indonesia": "True", "New Zealand": "True"}